{
  "Services & Pricing": "We offer a range of CA services including Company Incorporation, GST Filing, and Tax Advisory. You can find detailed pricing on our Pricing page.",
  "Book a Free Consultation": "Great! You can book a free consultation by visiting our Contact page or filling out the form on our website.",
  "GST / Filing Help": "We provide end-to-end GST support. Our team can help you with registration, monthly filings, and dispute resolution.",
  "Talk to a CA / Live Agent": "Our live agents are available from 9 AM to 6 PM IST. You can also reach us directly via WhatsApp or phone.",
  "Leave a Message": "Please leave your name, email, and message on our Contact page, and our team will get back to you within 24 hours."
}
